grdwindinversion/__init__.py
grdwindinversion/degrade.py
grdwindinversion/inversion.py
grdwindinversion/load_config.py
grdwindinversion/main.py
grdwindinversion/main_plot.py
grdwindinversion-999.dist-info/AUTHORS.rst
grdwindinversion-999.dist-info/LICENSE
grdwindinversion-999.dist-info/METADATA
grdwindinversion-999.dist-info/WHEEL
grdwindinversion-999.dist-info/top_level.txt
grdwindinversion-999.dist-info/RECORD
