Metadata-Version: 2.1
Name: grdwindinversion
Version: 999
Summary: Package to perform Wind inversion from GRD Level-1 SAR images
License: MIT
Classifier: Development Status :: 2 - Pre-Alpha
Classifier: Intended Audience :: Developers
Classifier: License :: OSI Approved :: MIT License
Classifier: Natural Language :: English
Classifier: Programming Language :: Python :: 3
Classifier: Programming Language :: Python :: 3.6
Classifier: Programming Language :: Python :: 3.7
Classifier: Programming Language :: Python :: 3.8
Classifier: Programming Language :: Python :: 3.9
Classifier: Programming Language :: Python :: 3.10
Classifier: Programming Language :: Python :: 3.11
Requires-Python: >=3.9
License-File: LICENSE
License-File: AUTHORS.rst
Requires-Dist: xsar
Requires-Dist: xsarsea
Requires-Dist: xarray
Requires-Dist: xarray-datatree
Requires-Dist: pyyaml
Requires-Dist: numpy
Requires-Dist: scipy
Requires-Dist: fsspec
Requires-Dist: aiohttp
